README.txt
setup.py
runprocess/__init__.py
runprocess/runprocess.py
runprocess.egg-info/PKG-INFO
runprocess.egg-info/SOURCES.txt
runprocess.egg-info/dependency_links.txt
runprocess.egg-info/not-zip-safe
runprocess.egg-info/requires.txt
runprocess.egg-info/top_level.txt