Metadata-Version: 1.1
Name: runprocess
Version: 0.14
Summary: allows you to run shell command and returns a dictionary with output and exit status
Home-page: http://example.com
Author: Banio Carpenter
Author-email: banio@mncarpenters.net
License: BSD
Platform: UNKNOWN
Classifier: Development Status :: 3 - Alpha
Classifier: Environment :: Web Environment
Classifier: Intended Audience :: Developers
Classifier: License :: OSI Approved :: BSD License
Classifier: Operating System :: OS Independent
Classifier: Programming Language :: Python :: 3.5
